rappf/__init__.py
rappf/art.py
rappf/dag.py
rappf/py.typed
rappf-0.2.dist-info/METADATA
rappf-0.2.dist-info/WHEEL
rappf-0.2.dist-info/top_level.txt
rappf-0.2.dist-info/RECORD
