Metadata-Version: 2.1
Name: rappf
Version: 0.2
Summary: Replayable App Framework
Home-page: https://github.com/apljungquist/rappf
Author: AP Ljungquist
Author-email: ap@ljungquist.eu
License: UNKNOWN
Platform: UNKNOWN
Requires-Python: >=3.9
Provides-Extra: examples
Requires-Dist: fire ; extra == 'examples'
